odoo/addons/stock_release_channel_shipment_lead_time/README.rst
odoo/addons/stock_release_channel_shipment_lead_time/__init__.py
odoo/addons/stock_release_channel_shipment_lead_time/__manifest__.py
odoo/addons/stock_release_channel_shipment_lead_time/i18n/fr.po
odoo/addons/stock_release_channel_shipment_lead_time/i18n/it.po
odoo/addons/stock_release_channel_shipment_lead_time/i18n/stock_release_channel_shipment_lead_time.pot
odoo/addons/stock_release_channel_shipment_lead_time/models/__init__.py
odoo/addons/stock_release_channel_shipment_lead_time/models/shipment_advice.py
odoo/addons/stock_release_channel_shipment_lead_time/models/stock_picking.py
odoo/addons/stock_release_channel_shipment_lead_time/models/stock_release_channel.py
odoo/addons/stock_release_channel_shipment_lead_time/readme/CONTRIBUTORS.md
odoo/addons/stock_release_channel_shipment_lead_time/readme/CREDITS.md
odoo/addons/stock_release_channel_shipment_lead_time/readme/DESCRIPTION.md
odoo/addons/stock_release_channel_shipment_lead_time/readme/ROADMAP.md
odoo/addons/stock_release_channel_shipment_lead_time/static/description/icon.png
odoo/addons/stock_release_channel_shipment_lead_time/static/description/index.html
odoo/addons/stock_release_channel_shipment_lead_time/tests/__init__.py
odoo/addons/stock_release_channel_shipment_lead_time/tests/test_assign_channel_shipment_date.py
odoo/addons/stock_release_channel_shipment_lead_time/tests/test_release_end_date.py
odoo/addons/stock_release_channel_shipment_lead_time/tests/test_release_shipment_date.py
odoo/addons/stock_release_channel_shipment_lead_time/views/shipment_advice_views.xml
odoo/addons/stock_release_channel_shipment_lead_time/views/stock_release_channel_views.xml
odoo/addons/stock_release_channel_shipment_lead_time/wizards/__init__.py
odoo/addons/stock_release_channel_shipment_lead_time/wizards/shipment_advice_planner.py
odoo_addon_stock_release_channel_shipment_lead_time-18.0.1.0.0.2.dist-info/METADATA
odoo_addon_stock_release_channel_shipment_lead_time-18.0.1.0.0.2.dist-info/WHEEL
odoo_addon_stock_release_channel_shipment_lead_time-18.0.1.0.0.2.dist-info/top_level.txt
odoo_addon_stock_release_channel_shipment_lead_time-18.0.1.0.0.2.dist-info/RECORD
